LICENSE
MANIFEST.in
README.md
setup.py
pythondemomessaging1/__init__.py
pythondemomessaging1/api_helper.py
pythondemomessaging1/configuration.py
pythondemomessaging1/decorators.py
pythondemomessaging1/pythondemomessaging_1_client.py
pythondemomessaging1.egg-info/PKG-INFO
pythondemomessaging1.egg-info/SOURCES.txt
pythondemomessaging1.egg-info/dependency_links.txt
pythondemomessaging1.egg-info/requires.txt
pythondemomessaging1.egg-info/top_level.txt
pythondemomessaging1/controllers/__init__.py
pythondemomessaging1/controllers/base_controller.py
pythondemomessaging1/controllers/delivery_reports_controller.py
pythondemomessaging1/controllers/messages_controller.py
pythondemomessaging1/controllers/replies_controller.py
pythondemomessaging1/exceptions/__init__.py
pythondemomessaging1/exceptions/api_exception.py
pythondemomessaging1/http/__init__.py
pythondemomessaging1/http/http_call_back.py
pythondemomessaging1/http/http_client.py
pythondemomessaging1/http/http_context.py
pythondemomessaging1/http/http_method_enum.py
pythondemomessaging1/http/http_request.py
pythondemomessaging1/http/http_response.py
pythondemomessaging1/http/requests_client.py
pythondemomessaging1/http/auth/__init__.py
pythondemomessaging1/http/auth/basic_auth.py
pythondemomessaging1/models/__init__.py
pythondemomessaging1/models/cancel_scheduled_message_request.py
pythondemomessaging1/models/check_delivery_reports_response.py
pythondemomessaging1/models/check_replies_response.py
pythondemomessaging1/models/confirm_delivery_reports_as_received_request.py
pythondemomessaging1/models/confirm_replies_as_received_request.py
pythondemomessaging1/models/format_enum.py
pythondemomessaging1/models/message.py
pythondemomessaging1/models/metadata.py
pythondemomessaging1/models/send_messages_request.py
pythondemomessaging1/models/send_messages_response.py
pythondemomessaging1/models/source_number_type_enum.py
pythondemomessaging1/models/status_enum.py
tests/__init__.py
tests/http_response_catcher.py
tests/test_helper.py
tests/controllers/__init__.py
tests/controllers/controller_test_base.py
tests/controllers/test_delivery_reports_controller.py
tests/controllers/test_replies_controller.py